molpipeline/__init__.py
molpipeline/error_handling.py
molpipeline/post_prediction.py
molpipeline/py.typed
molpipeline/abstract_pipeline_elements/__init__.py
molpipeline/abstract_pipeline_elements/core.py
molpipeline/abstract_pipeline_elements/any2mol/__init__.py
molpipeline/abstract_pipeline_elements/any2mol/string2mol.py
molpipeline/abstract_pipeline_elements/mol2any/__init__.py
molpipeline/abstract_pipeline_elements/mol2any/mol2bitvector.py
molpipeline/abstract_pipeline_elements/mol2any/mol2floatvector.py
molpipeline/abstract_pipeline_elements/mol2any/mol2string.py
molpipeline/abstract_pipeline_elements/mol2mol/__init__.py
molpipeline/abstract_pipeline_elements/mol2mol/filter.py
molpipeline/any2mol/__init__.py
molpipeline/any2mol/auto2mol.py
molpipeline/any2mol/bin2mol.py
molpipeline/any2mol/inchi2mol.py
molpipeline/any2mol/sdf2mol.py
molpipeline/any2mol/smiles2mol.py
molpipeline/estimators/__init__.py
molpipeline/estimators/connected_component_clustering.py
molpipeline/estimators/leader_picker_clustering.py
molpipeline/estimators/murcko_scaffold_clustering.py
molpipeline/estimators/nearest_neighbor.py
molpipeline/estimators/similarity_transformation.py
molpipeline/estimators/algorithm/__init__.py
molpipeline/estimators/algorithm/connected_component_clustering.py
molpipeline/estimators/algorithm/union_find.py
molpipeline/estimators/calibration/__init__.py
molpipeline/estimators/calibration/calibrated_classifier.py
molpipeline/estimators/chemprop/__init__.py
molpipeline/estimators/chemprop/abstract.py
molpipeline/estimators/chemprop/component_wrapper.py
molpipeline/estimators/chemprop/lightning_wrapper.py
molpipeline/estimators/chemprop/metric_wrapper.py
molpipeline/estimators/chemprop/models.py
molpipeline/estimators/chemprop/neural_fingerprint.py
molpipeline/estimators/chemprop/featurizer_wrapper/__init__.py
molpipeline/estimators/chemprop/featurizer_wrapper/graph_wrapper.py
molpipeline/experimental/__init__.py
molpipeline/experimental/custom_filter.py
molpipeline-0.12.0.dist-info/licenses/LICENSE
molpipeline-0.12.0.dist-info/METADATA
molpipeline-0.12.0.dist-info/WHEEL
molpipeline-0.12.0.dist-info/top_level.txt
molpipeline-0.12.0.dist-info/RECORD
