Metadata-Version: 2.4
Name: molpipeline
Version: 0.12.0
Summary: Integration of rdkit functionality into sklearn pipelines.
Author: Christian W. Feldmann, Jennifer Hemmerich, Jochen Sieg, Kyriakos Soulios
License-File: LICENSE
Requires-Dist: crepes>=0.8.0
Requires-Dist: joblib>=1.3.0
Requires-Dist: loguru>=0.7.3
Requires-Dist: matplotlib>=3.10.1
Requires-Dist: numpy>=1.26.4
Requires-Dist: pandas>=2.2.3
Requires-Dist: rdkit>=2023.9.1
Requires-Dist: scikit-learn>=1.8.0
Requires-Dist: scipy>=1.15.2
Requires-Dist: shap>=0.47.1
Requires-Dist: typing-extensions>=4.13.1
Provides-Extra: chemprop
Requires-Dist: chemprop<2.3.0,>=2.2.0; extra == "chemprop"
Requires-Dist: dvc>=3.64.1; extra == "chemprop"
Requires-Dist: lightning>=2.5.1; extra == "chemprop"
Requires-Dist: requests>=2.32.5; extra == "chemprop"
Provides-Extra: notebooks
Requires-Dist: jupyterlab>=4.4.0; extra == "notebooks"
Requires-Dist: seaborn>=0.13.2; extra == "notebooks"
Dynamic: license-file
